{
  "fetched_at": "2026-04-10T22:32:02.187391Z",
  "count": 39,
  "source": "CoinGecko (coingecko.com)",
  "attribution": "Data provided by CoinGecko",
  "tokens": [
    {
      "ticker": "ANIMUS",
      "coingecko_id": "animus",
      "name": "Animus",
      "sector": "Token",
      "price": 1.306e-05,
      "currency": "USD",
      "change_pct": 7.14,
      "volume": null,
      "date": "2026-04-10",
      "source": "CoinGecko"
    },
    {
      "ticker": "AUKI",
      "coingecko_id": "auki-labs",
      "name": "Auki",
      "sector": "Token",
      "price": 0.00571482,
      "currency": "USD",
      "change_pct": -5.14,
      "volume": null,
      "date": "2026-04-10",
      "source": "CoinGecko"
    },
    {
      "ticker": "ATNM",
      "coingecko_id": "autonoma-network",
      "name": "Autonoma Network",
      "sector": "Token",
      "price": 3.84e-06,
      "currency": "USD",
      "change_pct": null,
      "volume": null,
      "date": "2026-04-10",
      "source": "CoinGecko"
    },
    {
      "ticker": "CODEC",
      "coingecko_id": "codec-flow",
      "name": "Codec Flow",
      "sector": "Token",
      "price": 0.00243912,
      "currency": "USD",
      "change_pct": 0.94,
      "volume": null,
      "date": "2026-04-10",
      "source": "CoinGecko"
    },
    {
      "ticker": "DPTX",
      "coingecko_id": "deeptics",
      "name": "DEEPTICS",
      "sector": "Token",
      "price": 0.0005659,
      "currency": "USD",
      "change_pct": null,
      "volume": null,
      "date": "2026-04-10",
      "source": "CoinGecko"
    },
    {
      "ticker": "$CPT",
      "coingecko_id": "empulser-enterprises",
      "name": "Empulser Enterprises",
      "sector": "Token",
      "price": 0.074453,
      "currency": "USD",
      "change_pct": 0.09,
      "volume": null,
      "date": "2026-04-10",
      "source": "CoinGecko"
    },
    {
      "ticker": "ROBO",
      "coingecko_id": "robo-token-2",
      "name": "Fabric Protocol",
      "sector": "Token",
      "price": 0.01703289,
      "currency": "USD",
      "change_pct": 0.51,
      "volume": null,
      "date": "2026-04-10",
      "source": "CoinGecko"
    },
    {
      "ticker": "FORMA",
      "coingecko_id": "forma-robotics",
      "name": "Forma Robotics",
      "sector": "Token",
      "price": 0.00029758,
      "currency": "USD",
      "change_pct": -2.92,
      "volume": null,
      "date": "2026-04-10",
      "source": "CoinGecko"
    },
    {
      "ticker": "GEOD",
      "coingecko_id": "geodnet",
      "name": "Geodnet",
      "sector": "Token",
      "price": 0.131606,
      "currency": "USD",
      "change_pct": -2.41,
      "volume": null,
      "date": "2026-04-10",
      "source": "CoinGecko"
    },
    {
      "ticker": "BREW",
      "coingecko_id": "homebrew-robotics-club",
      "name": "Homebrew Robotics Club",
      "sector": "Token",
      "price": 0.00084205,
      "currency": "USD",
      "change_pct": 21.32,
      "volume": null,
      "date": "2026-04-10",
      "source": "CoinGecko"
    },
    {
      "ticker": "IOTX",
      "coingecko_id": "iotex",
      "name": "IoTeX",
      "sector": "Token",
      "price": 0.00467345,
      "currency": "USD",
      "change_pct": 0.3,
      "volume": null,
      "date": "2026-04-10",
      "source": "CoinGecko"
    },
    {
      "ticker": "JOJO",
      "coingecko_id": "jojoworld",
      "name": "JojoWorld",
      "sector": "Token",
      "price": 0.00407945,
      "currency": "USD",
      "change_pct": -3.51,
      "volume": null,
      "date": "2026-04-10",
      "source": "CoinGecko"
    },
    {
      "ticker": "KAGE",
      "coingecko_id": "kage-network",
      "name": "KAGE Network",
      "sector": "Token",
      "price": 0.00034704,
      "currency": "USD",
      "change_pct": 0.3,
      "volume": null,
      "date": "2026-04-10",
      "source": "CoinGecko"
    },
    {
      "ticker": "MECHA",
      "coingecko_id": "mechaos",
      "name": "MechaOs",
      "sector": "Token",
      "price": 6.773e-05,
      "currency": "USD",
      "change_pct": null,
      "volume": null,
      "date": "2026-04-10",
      "source": "CoinGecko"
    },
    {
      "ticker": "EMDR",
      "coingecko_id": "modulr",
      "name": "Modulr",
      "sector": "Token",
      "price": 2.28,
      "currency": "USD",
      "change_pct": 17.91,
      "volume": null,
      "date": "2026-04-10",
      "source": "CoinGecko"
    },
    {
      "ticker": "NATIX",
      "coingecko_id": "natix-network",
      "name": "NATIX Network",
      "sector": "Token",
      "price": 9.377e-05,
      "currency": "USD",
      "change_pct": -4.48,
      "volume": null,
      "date": "2026-04-10",
      "source": "CoinGecko"
    },
    {
      "ticker": "OP",
      "coingecko_id": "one-path",
      "name": "One Path",
      "sector": "Token",
      "price": 4.428e-05,
      "currency": "USD",
      "change_pct": 7.34,
      "volume": null,
      "date": "2026-04-10",
      "source": "CoinGecko"
    },
    {
      "ticker": "ONO",
      "coingecko_id": "onocoy-token",
      "name": "Onocoy Token",
      "sector": "Token",
      "price": 0.02729218,
      "currency": "USD",
      "change_pct": 3.91,
      "volume": null,
      "date": "2026-04-10",
      "source": "CoinGecko"
    },
    {
      "ticker": "OPAN",
      "coingecko_id": "opanarchy",
      "name": "Opanarchy",
      "sector": "Token",
      "price": 4.31e-06,
      "currency": "USD",
      "change_pct": null,
      "volume": null,
      "date": "2026-04-10",
      "source": "CoinGecko"
    },
    {
      "ticker": "OPUS",
      "coingecko_id": "opus-2",
      "name": "Opus Genesis",
      "sector": "Token",
      "price": 0.00178659,
      "currency": "USD",
      "change_pct": 0.9,
      "volume": null,
      "date": "2026-04-10",
      "source": "CoinGecko"
    },
    {
      "ticker": "OVR",
      "coingecko_id": "ovr",
      "name": "Ovr",
      "sector": "Token",
      "price": 0.04034149,
      "currency": "USD",
      "change_pct": 1.75,
      "volume": null,
      "date": "2026-04-10",
      "source": "CoinGecko"
    },
    {
      "ticker": "QACE",
      "coingecko_id": "qace-dynamics",
      "name": "Qace Dynamics",
      "sector": "Token",
      "price": 1.443e-05,
      "currency": "USD",
      "change_pct": -0.37,
      "volume": null,
      "date": "2026-04-10",
      "source": "CoinGecko"
    },
    {
      "ticker": "ROBA",
      "coingecko_id": "roba",
      "name": "ROBA",
      "sector": "Token",
      "price": 0.00013838,
      "currency": "USD",
      "change_pct": -0.53,
      "volume": null,
      "date": "2026-04-10",
      "source": "CoinGecko"
    },
    {
      "ticker": "ROVR",
      "coingecko_id": "rovr-network",
      "name": "ROVR Network",
      "sector": "Token",
      "price": 0.00298091,
      "currency": "USD",
      "change_pct": -2.47,
      "volume": null,
      "date": "2026-04-10",
      "source": "CoinGecko"
    },
    {
      "ticker": "RICE",
      "coingecko_id": "rice-ai",
      "name": "Rice AI",
      "sector": "Token",
      "price": 0.00405392,
      "currency": "USD",
      "change_pct": 4.63,
      "volume": null,
      "date": "2026-04-10",
      "source": "CoinGecko"
    },
    {
      "ticker": "ROBCO",
      "coingecko_id": "robco-network",
      "name": "RobCo Network",
      "sector": "Token",
      "price": 0.00267454,
      "currency": "USD",
      "change_pct": null,
      "volume": null,
      "date": "2026-04-10",
      "source": "CoinGecko"
    },
    {
      "ticker": "ROBOT",
      "coingecko_id": "robostack",
      "name": "RoboStack",
      "sector": "Token",
      "price": 0.00017025,
      "currency": "USD",
      "change_pct": -0.39,
      "volume": null,
      "date": "2026-04-10",
      "source": "CoinGecko"
    },
    {
      "ticker": "XRT",
      "coingecko_id": "robonomics-network",
      "name": "Robonomics Network",
      "sector": "Token",
      "price": 0.04696294,
      "currency": "USD",
      "change_pct": -2.22,
      "volume": null,
      "date": "2026-04-10",
      "source": "CoinGecko"
    },
    {
      "ticker": "RBR",
      "coingecko_id": "robora",
      "name": "Robora",
      "sector": "Token",
      "price": 0.00105253,
      "currency": "USD",
      "change_pct": 19.95,
      "volume": null,
      "date": "2026-04-10",
      "source": "CoinGecko"
    },
    {
      "ticker": "ROX",
      "coingecko_id": "robotexon",
      "name": "Robotexon",
      "sector": "Token",
      "price": 0.00043533,
      "currency": "USD",
      "change_pct": null,
      "volume": null,
      "date": "2026-04-10",
      "source": "CoinGecko"
    },
    {
      "ticker": "ROKO",
      "coingecko_id": "roko-network",
      "name": "Roko Network",
      "sector": "Token",
      "price": 4.31e-06,
      "currency": "USD",
      "change_pct": -10.66,
      "volume": null,
      "date": "2026-04-10",
      "source": "CoinGecko"
    },
    {
      "ticker": "SLC",
      "coingecko_id": "silencio",
      "name": "Silencio",
      "sector": "Token",
      "price": 3.439e-05,
      "currency": "USD",
      "change_pct": -6.29,
      "volume": null,
      "date": "2026-04-10",
      "source": "CoinGecko"
    },
    {
      "ticker": "SMPL",
      "coingecko_id": "simple-ai",
      "name": "Simple AI",
      "sector": "Token",
      "price": 0.00069225,
      "currency": "USD",
      "change_pct": -0.29,
      "volume": null,
      "date": "2026-04-10",
      "source": "CoinGecko"
    },
    {
      "ticker": "SPAWN",
      "coingecko_id": "spawn",
      "name": "Spawn",
      "sector": "Token",
      "price": 2.572e-05,
      "currency": "USD",
      "change_pct": -2.72,
      "volume": null,
      "date": "2026-04-10",
      "source": "CoinGecko"
    },
    {
      "ticker": "VADER",
      "coingecko_id": "vaderai-by-virtuals",
      "name": "Vader",
      "sector": "Token",
      "price": 0.00114857,
      "currency": "USD",
      "change_pct": -3.77,
      "volume": null,
      "date": "2026-04-10",
      "source": "CoinGecko"
    },
    {
      "ticker": "VIRTUAL",
      "coingecko_id": "virtual-protocol",
      "name": "Virtuals Protocol",
      "sector": "Token",
      "price": 0.680448,
      "currency": "USD",
      "change_pct": -0.24,
      "volume": null,
      "date": "2026-04-10",
      "source": "CoinGecko"
    },
    {
      "ticker": "SHOW",
      "coingecko_id": "vitanova",
      "name": "VitaNova",
      "sector": "Token",
      "price": 0.00013078,
      "currency": "USD",
      "change_pct": -11.92,
      "volume": null,
      "date": "2026-04-10",
      "source": "CoinGecko"
    },
    {
      "ticker": "DEUS",
      "coingecko_id": "xmaquina",
      "name": "XMAQUINA",
      "sector": "Token",
      "price": null,
      "currency": "USD",
      "change_pct": null,
      "volume": null,
      "date": "2026-04-10",
      "source": "CoinGecko"
    },
    {
      "ticker": "PEAQ",
      "coingecko_id": "peaq-2",
      "name": "peaq",
      "sector": "Token",
      "price": 0.01352019,
      "currency": "USD",
      "change_pct": 0.34,
      "volume": null,
      "date": "2026-04-10",
      "source": "CoinGecko"
    }
  ]
}